{
  "city_name": "Hervey Bay",
  "forecasts": {
    "2026-02-04": {
      "0": {
        "forecast": "Cloudy. Slight chance of a shower this morning. Winds southeasterly 20 to 30 km/h.",
        "icon_code": 4,
        "precipitation_prob": "20%",
        "precis": "Cloudy.",
        "temp_max": 29,
        "temp_min": null
      },
      "1": {
        "forecast": "Cloudy. Slight chance of a shower in the morning. Winds southeasterly 20 to 30 km/h.",
        "icon_code": 4,
        "precipitation_prob": "20%",
        "precis": "Cloudy.",
        "temp_max": 29,
        "temp_min": 22
      },
      "2": {
        "forecast": "Cloudy. Slight chance of a shower, most likely in the early morning. Winds southeasterly 20 to 30 km/h.",
        "icon_code": 4,
        "precipitation_prob": "30%",
        "precis": "Cloudy.",
        "temp_max": 29,
        "temp_min": 22
      },
      "3": {
        "forecast": "Cloudy. Slight chance of a shower, most likely in the morning. Winds southeasterly 25 to 35 km/h.",
        "icon_code": 4,
        "precipitation_prob": "20%",
        "precis": "Cloudy.",
        "temp_max": 29,
        "temp_min": 22
      },
      "4": {
        "forecast": "Cloudy. Medium chance of showers, most likely in the morning and afternoon. Winds southeasterly 20 to 30 km/h.",
        "icon_code": 11,
        "precipitation_prob": "60%",
        "precis": "Shower or two.",
        "temp_max": 29,
        "temp_min": 22
      },
      "5": {
        "forecast": "Cloudy. High chance of showers, most likely during the morning. The chance of a thunderstorm. Winds southeasterly 20 to 30 km/h.",
        "icon_code": 11,
        "precipitation_prob": "70%",
        "precis": "Shower or two.",
        "temp_max": 30,
        "temp_min": 22
      },
      "6": {
        "forecast": "Partly cloudy. Medium chance of showers. The chance of a thunderstorm. Winds southeasterly 15 to 20 km/h tending easterly 15 to 25 km/h during the morning.",
        "icon_code": 17,
        "precipitation_prob": "40%",
        "precis": "Possible shower.",
        "temp_max": 31,
        "temp_min": 23
      },
      "7": {
        "forecast": "Partly cloudy. Medium chance of showers. The chance of a thunderstorm. Light winds becoming easterly 15 to 25 km/h during the morning.",
        "icon_code": 17,
        "precipitation_prob": "40%",
        "precis": "Possible shower.",
        "temp_max": 31,
        "temp_min": 23
      }
    },
    "2026-02-05": {
      "1": {
        "forecast": "Partly cloudy. Winds southeasterly 15 to 20 km/h becoming light before dawn then becoming southeasterly 20 to 30 km/h in the morning.",
        "icon_code": 3,
        "precipitation_prob": "5%",
        "precis": "Partly cloudy.",
        "temp_max": 30,
        "temp_min": 22
      },
      "2": {
        "forecast": "Partly cloudy. Winds southeasterly 15 to 20 km/h becoming light before dawn then becoming southeasterly 20 to 30 km/h in the morning.",
        "icon_code": 3,
        "precipitation_prob": "10%",
        "precis": "Partly cloudy.",
        "temp_max": 30,
        "temp_min": 22
      },
      "3": {
        "forecast": "Partly cloudy. Winds southeasterly 20 to 30 km/h becoming light during the evening.",
        "icon_code": 3,
        "precipitation_prob": "10%",
        "precis": "Partly cloudy.",
        "temp_max": 30,
        "temp_min": 22
      },
      "4": {
        "forecast": "Partly cloudy. Slight chance of a shower. Winds southeasterly 20 to 30 km/h becoming light during the evening.",
        "icon_code": 3,
        "precipitation_prob": "20%",
        "precis": "Partly cloudy.",
        "temp_max": 30,
        "temp_min": 22
      },
      "5": {
        "forecast": "Partly cloudy. Slight chance of a shower, most likely during the morning. Winds southeasterly 20 to 30 km/h.",
        "icon_code": 3,
        "precipitation_prob": "30%",
        "precis": "Partly cloudy.",
        "temp_max": 31,
        "temp_min": 23
      },
      "6": {
        "forecast": "Partly cloudy. Slight chance of a shower. The chance of a thunderstorm. Winds southeasterly 20 to 30 km/h.",
        "icon_code": 3,
        "precipitation_prob": "30%",
        "precis": "Partly cloudy.",
        "temp_max": 31,
        "temp_min": 23
      },
      "7": {
        "forecast": "Partly cloudy. Medium chance of showers. The chance of a thunderstorm. Light winds becoming east to southeasterly 15 to 25 km/h during the morning.",
        "icon_code": 17,
        "precipitation_prob": "40%",
        "precis": "Possible shower.",
        "temp_max": 31,
        "temp_min": 23
      }
    },
    "2026-02-06": {
      "2": {
        "forecast": "Partly cloudy. Light winds becoming southeasterly 20 to 30 km/h during the morning.",
        "icon_code": 3,
        "precipitation_prob": "10%",
        "precis": "Partly cloudy.",
        "temp_max": 30,
        "temp_min": 22
      },
      "3": {
        "forecast": "Partly cloudy. Slight chance of a shower. Light winds becoming southeasterly 20 to 30 km/h during the morning.",
        "icon_code": 3,
        "precipitation_prob": "20%",
        "precis": "Partly cloudy.",
        "temp_max": 30,
        "temp_min": 22
      },
      "4": {
        "forecast": "Partly cloudy. Slight chance of a shower. Light winds becoming southeasterly 20 to 30 km/h during the morning then becoming light during the evening.",
        "icon_code": 3,
        "precipitation_prob": "20%",
        "precis": "Partly cloudy.",
        "temp_max": 30,
        "temp_min": 22
      },
      "5": {
        "forecast": "Partly cloudy. Slight chance of a shower. Light winds becoming southeasterly 20 to 30 km/h during the morning.",
        "icon_code": 3,
        "precipitation_prob": "20%",
        "precis": "Partly cloudy.",
        "temp_max": 30,
        "temp_min": 22
      },
      "6": {
        "forecast": "Partly cloudy. Slight chance of a shower. Light winds becoming southeasterly 15 to 25 km/h during the morning.",
        "icon_code": 3,
        "precipitation_prob": "30%",
        "precis": "Partly cloudy.",
        "temp_max": 30,
        "temp_min": 22
      },
      "7": {
        "forecast": "Partly cloudy. Slight chance of a shower. Light winds becoming southeasterly 20 to 30 km/h during the morning.",
        "icon_code": 3,
        "precipitation_prob": "30%",
        "precis": "Partly cloudy.",
        "temp_max": 31,
        "temp_min": 22
      }
    },
    "2026-02-07": {
      "3": {
        "forecast": "Partly cloudy. Slight chance of a shower. Winds southeasterly 20 to 30 km/h.",
        "icon_code": 3,
        "precipitation_prob": "30%",
        "precis": "Partly cloudy.",
        "temp_max": 30,
        "temp_min": 22
      },
      "4": {
        "forecast": "Partly cloudy. Slight chance of a shower. Winds southeasterly 15 to 25 km/h becoming light during the evening.",
        "icon_code": 3,
        "precipitation_prob": "20%",
        "precis": "Partly cloudy.",
        "temp_max": 31,
        "temp_min": 22
      },
      "5": {
        "forecast": "Partly cloudy. Slight chance of a shower. Light winds becoming east to southeasterly 15 to 25 km/h during the morning.",
        "icon_code": 3,
        "precipitation_prob": "20%",
        "precis": "Partly cloudy.",
        "temp_max": 30,
        "temp_min": 22
      },
      "6": {
        "forecast": "Partly cloudy. Slight chance of a shower. Light winds becoming east to southeasterly 15 to 25 km/h during the morning.",
        "icon_code": 3,
        "precipitation_prob": "20%",
        "precis": "Partly cloudy.",
        "temp_max": 31,
        "temp_min": 22
      },
      "7": {
        "forecast": "Partly cloudy. Slight chance of a shower. Light winds becoming east to southeasterly 15 to 25 km/h during the morning.",
        "icon_code": 3,
        "precipitation_prob": "30%",
        "precis": "Partly cloudy.",
        "temp_max": 31,
        "temp_min": 23
      }
    },
    "2026-02-08": {
      "4": {
        "forecast": "Partly cloudy. Slight chance of a shower. Winds east to southeasterly 15 to 25 km/h.",
        "icon_code": 3,
        "precipitation_prob": "20%",
        "precis": "Partly cloudy.",
        "temp_max": 31,
        "temp_min": 22
      },
      "5": {
        "forecast": "Partly cloudy. Slight chance of a shower. Winds southeasterly 15 to 20 km/h tending easterly 15 to 25 km/h during the day.",
        "icon_code": 3,
        "precipitation_prob": "20%",
        "precis": "Partly cloudy.",
        "temp_max": 31,
        "temp_min": 22
      },
      "6": {
        "forecast": "Partly cloudy. Slight chance of a shower. Winds southeasterly 15 to 20 km/h tending easterly 15 to 25 km/h during the day.",
        "icon_code": 3,
        "precipitation_prob": "20%",
        "precis": "Partly cloudy.",
        "temp_max": 31,
        "temp_min": 22
      },
      "7": {
        "forecast": "Partly cloudy. Slight chance of a shower. Winds southeasterly 15 to 20 km/h tending easterly 15 to 25 km/h during the day.",
        "icon_code": 3,
        "precipitation_prob": "20%",
        "precis": "Partly cloudy.",
        "temp_max": 32,
        "temp_min": 22
      }
    },
    "2026-02-09": {
      "5": {
        "forecast": "Partly cloudy. Slight chance of a shower. Light winds becoming easterly 15 to 25 km/h during the day.",
        "icon_code": 3,
        "precipitation_prob": "20%",
        "precis": "Partly cloudy.",
        "temp_max": 32,
        "temp_min": 22
      },
      "6": {
        "forecast": "Partly cloudy. Slight chance of a shower. Light winds becoming easterly 15 to 25 km/h during the day.",
        "icon_code": 3,
        "precipitation_prob": "20%",
        "precis": "Partly cloudy.",
        "temp_max": 32,
        "temp_min": 22
      },
      "7": {
        "forecast": "Partly cloudy. Slight chance of a shower. Light winds becoming easterly 15 to 25 km/h during the day.",
        "icon_code": 3,
        "precipitation_prob": "30%",
        "precis": "Partly cloudy.",
        "temp_max": 32,
        "temp_min": 22
      }
    },
    "2026-02-10": {
      "6": {
        "forecast": "Partly cloudy. Slight chance of a shower. Light winds becoming east to northeasterly 15 to 25 km/h during the day.",
        "icon_code": 3,
        "precipitation_prob": "20%",
        "precis": "Partly cloudy.",
        "temp_max": 32,
        "temp_min": 23
      },
      "7": {
        "forecast": "Partly cloudy. Medium chance of showers. Light winds becoming northeasterly 15 to 25 km/h during the day.",
        "icon_code": 17,
        "precipitation_prob": "40%",
        "precis": "Possible shower.",
        "temp_max": 32,
        "temp_min": 23
      }
    }
  },
  "product_id": "IDQ10910",
  "state": "QLD",
  "timezone": "EST"
}