{
  "city_name": "Darwin",
  "forecasts": {
    "2026-03-03": {
      "0": {
        "forecast": "Cloudy. Very high chance of showers. The chance of a thunderstorm from the late morning. Winds west to northwesterly 15 to 25 km/h.",
        "icon_code": 16,
        "precipitation_prob": "95%",
        "precis": "Showers. Possible storm.",
        "temp_max": 30,
        "temp_min": null
      },
      "1": {
        "forecast": "Cloudy. Very high chance of showers. The chance of a thunderstorm. Winds westerly 15 to 20 km/h turning northwesterly 20 to 30 km/h early in the morning.",
        "icon_code": 16,
        "precipitation_prob": "95%",
        "precis": "Showers. Possible storm.",
        "temp_max": 31,
        "temp_min": 25
      },
      "2": {
        "forecast": "Partly cloudy. Very high chance of showers. The chance of a thunderstorm. Winds northwesterly 15 to 25 km/h.",
        "icon_code": 11,
        "precipitation_prob": "95%",
        "precis": "Showers.",
        "temp_max": 31,
        "temp_min": 25
      },
      "3": {
        "forecast": "Partly cloudy. Very high chance of showers. The chance of a thunderstorm in the afternoon and evening. Winds westerly 15 to 25 km/h increasing to 30 km/h before turning northwesterly 15 to 25 km/h during the day.",
        "icon_code": 11,
        "precipitation_prob": "95%",
        "precis": "Showers.",
        "temp_max": 31,
        "temp_min": 26
      },
      "4": {
        "forecast": "Cloudy. Very high chance of showers. The chance of a thunderstorm in the afternoon and evening. Winds northwesterly 20 to 30 km/h.",
        "icon_code": 16,
        "precipitation_prob": "95%",
        "precis": "Showers. Possible storm.",
        "temp_max": 31,
        "temp_min": 25
      },
      "5": {
        "forecast": "Cloudy. Very high chance of showers. A thunderstorm likely. Winds west to northwesterly 20 to 30 km/h.",
        "icon_code": 16,
        "precipitation_prob": "95%",
        "precis": "Showers. Storm.",
        "temp_max": 31,
        "temp_min": 25
      },
      "6": {
        "forecast": "Cloudy. Very high chance of showers. The chance of a thunderstorm. Winds westerly 20 to 30 km/h.",
        "icon_code": 11,
        "precipitation_prob": "95%",
        "precis": "Showers.",
        "temp_max": 30,
        "temp_min": 26
      },
      "7": {
        "forecast": "Cloudy. Very high chance of showers. The chance of a thunderstorm. Winds westerly 20 to 30 km/h.",
        "icon_code": 11,
        "precipitation_prob": "95%",
        "precis": "Showers.",
        "temp_max": 31,
        "temp_min": 25
      }
    },
    "2026-03-04": {
      "1": {
        "forecast": "Partly cloudy. Very high chance of showers, most likely in the morning and afternoon. The chance of a thunderstorm in the afternoon and evening. Winds westerly 15 to 25 km/h.",
        "icon_code": 16,
        "precipitation_prob": "90%",
        "precis": "Showers. Possible afternoon storm.",
        "temp_max": 31,
        "temp_min": 26
      },
      "2": {
        "forecast": "Cloudy. Very high chance of showers, most likely in the morning and afternoon. The chance of a thunderstorm in the morning and afternoon. Winds westerly 15 to 25 km/h.",
        "icon_code": 16,
        "precipitation_prob": "95%",
        "precis": "Showers. Possible storm.",
        "temp_max": 31,
        "temp_min": 26
      },
      "3": {
        "forecast": "Partly cloudy. Very high chance of showers. The chance of a thunderstorm. Winds westerly 15 to 25 km/h.",
        "icon_code": 11,
        "precipitation_prob": "95%",
        "precis": "Showers.",
        "temp_max": 30,
        "temp_min": 26
      },
      "4": {
        "forecast": "Cloudy. Very high chance of showers. The chance of a thunderstorm in the morning and afternoon. Winds northwesterly 20 to 30 km/h.",
        "icon_code": 16,
        "precipitation_prob": "95%",
        "precis": "Showers. Possible afternoon storm.",
        "temp_max": 31,
        "temp_min": 25
      },
      "5": {
        "forecast": "Partly cloudy. Very high chance of showers. A thunderstorm likely. Winds northwesterly 15 to 25 km/h.",
        "icon_code": 16,
        "precipitation_prob": "95%",
        "precis": "Showers. Storm.",
        "temp_max": 31,
        "temp_min": 26
      },
      "6": {
        "forecast": "Cloudy. Very high chance of showers. The chance of a thunderstorm. Winds northwesterly 20 to 30 km/h.",
        "icon_code": 11,
        "precipitation_prob": "90%",
        "precis": "Showers.",
        "temp_max": 30,
        "temp_min": 25
      },
      "7": {
        "forecast": "Cloudy. Very high chance of showers. The chance of a thunderstorm. Winds westerly 20 to 30 km/h.",
        "icon_code": 11,
        "precipitation_prob": "90%",
        "precis": "Showers.",
        "temp_max": 31,
        "temp_min": 25
      }
    },
    "2026-03-05": {
      "2": {
        "forecast": "Partly cloudy. High chance of showers. The chance of a thunderstorm in the afternoon and evening. Winds westerly 15 to 25 km/h.",
        "icon_code": 11,
        "precipitation_prob": "80%",
        "precis": "Showers.",
        "temp_max": 31,
        "temp_min": 26
      },
      "3": {
        "forecast": "Partly cloudy. Very high chance of showers. The chance of a thunderstorm in the afternoon and evening. Winds westerly 15 to 25 km/h.",
        "icon_code": 11,
        "precipitation_prob": "90%",
        "precis": "Showers.",
        "temp_max": 31,
        "temp_min": 25
      },
      "4": {
        "forecast": "Partly cloudy. Very high chance of showers. The chance of a thunderstorm in the afternoon and evening. Winds westerly 15 to 25 km/h.",
        "icon_code": 16,
        "precipitation_prob": "90%",
        "precis": "Showers. Possible afternoon storm.",
        "temp_max": 31,
        "temp_min": 25
      },
      "5": {
        "forecast": "Partly cloudy. Very high chance of showers. The chance of a thunderstorm. Winds northwesterly 15 to 20 km/h turning westerly 15 to 25 km/h during the morning.",
        "icon_code": 16,
        "precipitation_prob": "90%",
        "precis": "Showers. Possible storm.",
        "temp_max": 31,
        "temp_min": 26
      },
      "6": {
        "forecast": "Partly cloudy. High chance of showers. The chance of a thunderstorm. Winds northwesterly 15 to 20 km/h turning westerly 15 to 25 km/h during the morning.",
        "icon_code": 16,
        "precipitation_prob": "80%",
        "precis": "Showers. Possible storm.",
        "temp_max": 31,
        "temp_min": 25
      },
      "7": {
        "forecast": "Partly cloudy. Very high chance of showers. The chance of a thunderstorm. Winds northwesterly 15 to 25 km/h.",
        "icon_code": 11,
        "precipitation_prob": "90%",
        "precis": "Showers.",
        "temp_max": 31,
        "temp_min": 25
      }
    },
    "2026-03-06": {
      "3": {
        "forecast": "Partly cloudy. Very high chance of showers. The chance of a thunderstorm in the afternoon and evening. Winds westerly 15 to 25 km/h.",
        "icon_code": 11,
        "precipitation_prob": "90%",
        "precis": "Showers.",
        "temp_max": 30,
        "temp_min": 25
      },
      "4": {
        "forecast": "Cloudy. Very high chance of showers. The chance of a thunderstorm in the afternoon and evening. Winds westerly 15 to 25 km/h.",
        "icon_code": 11,
        "precipitation_prob": "90%",
        "precis": "Showers.",
        "temp_max": 30,
        "temp_min": 24
      },
      "5": {
        "forecast": "Cloudy. Very high chance of showers. The chance of a thunderstorm. Winds westerly 15 to 25 km/h.",
        "icon_code": 16,
        "precipitation_prob": "90%",
        "precis": "Showers. Possible storm.",
        "temp_max": 31,
        "temp_min": 25
      },
      "6": {
        "forecast": "Partly cloudy. High chance of showers. The chance of a thunderstorm. Winds westerly 15 to 20 km/h.",
        "icon_code": 16,
        "precipitation_prob": "80%",
        "precis": "Showers. Possible storm.",
        "temp_max": 31,
        "temp_min": 25
      },
      "7": {
        "forecast": "Partly cloudy. High chance of showers. The chance of a thunderstorm. Winds westerly 15 to 20 km/h.",
        "icon_code": 16,
        "precipitation_prob": "80%",
        "precis": "Showers. Possible storm.",
        "temp_max": 32,
        "temp_min": 25
      }
    },
    "2026-03-07": {
      "4": {
        "forecast": "Cloudy. Very high chance of showers. The chance of a thunderstorm later in the day. Winds westerly 15 to 25 km/h.",
        "icon_code": 16,
        "precipitation_prob": "90%",
        "precis": "Showers. Possible storm.",
        "temp_max": 30,
        "temp_min": 25
      },
      "5": {
        "forecast": "Cloudy. Very high chance of showers. The chance of a thunderstorm. Winds westerly 15 to 25 km/h.",
        "icon_code": 16,
        "precipitation_prob": "90%",
        "precis": "Showers. Possible storm.",
        "temp_max": 30,
        "temp_min": 25
      },
      "6": {
        "forecast": "Cloudy. Very high chance of showers. The chance of a thunderstorm. Winds westerly 15 to 25 km/h.",
        "icon_code": 16,
        "precipitation_prob": "90%",
        "precis": "Showers. Possible storm.",
        "temp_max": 31,
        "temp_min": 26
      },
      "7": {
        "forecast": "Partly cloudy. High chance of showers. The chance of a thunderstorm. Winds westerly 15 to 20 km/h.",
        "icon_code": 16,
        "precipitation_prob": "80%",
        "precis": "Showers. Possible storm.",
        "temp_max": 32,
        "temp_min": 25
      }
    },
    "2026-03-08": {
      "5": {
        "forecast": "Cloudy. Very high chance of showers. The chance of a thunderstorm. Winds westerly 20 to 30 km/h.",
        "icon_code": 16,
        "precipitation_prob": "90%",
        "precis": "Showers. Possible storm.",
        "temp_max": 31,
        "temp_min": 25
      },
      "6": {
        "forecast": "Partly cloudy. Very high chance of showers. The chance of a thunderstorm. Winds westerly 15 to 25 km/h.",
        "icon_code": 16,
        "precipitation_prob": "90%",
        "precis": "Showers. Possible storm.",
        "temp_max": 31,
        "temp_min": 25
      },
      "7": {
        "forecast": "Partly cloudy. High chance of showers. The chance of a thunderstorm. Winds west to northwesterly 15 to 25 km/h.",
        "icon_code": 16,
        "precipitation_prob": "80%",
        "precis": "Showers. Possible storm.",
        "temp_max": 32,
        "temp_min": 26
      }
    },
    "2026-03-09": {
      "6": {
        "forecast": "Partly cloudy. High chance of showers. A thunderstorm likely. Winds westerly 15 to 25 km/h.",
        "icon_code": 16,
        "precipitation_prob": "80%",
        "precis": "Showers. Storm.",
        "temp_max": 32,
        "temp_min": 25
      },
      "7": {
        "forecast": "Partly cloudy. High chance of showers. The chance of a thunderstorm. Winds west to northwesterly 15 to 20 km/h.",
        "icon_code": 16,
        "precipitation_prob": "80%",
        "precis": "Showers. Possible storm.",
        "temp_max": 31,
        "temp_min": 25
      }
    }
  },
  "product_id": "IDD10150",
  "state": "NT",
  "timezone": "CST"
}