{
  "city_name": "Latrobe Valley",
  "forecasts": {
    "2025-12-22": {
      "0": {
        "forecast": "Mostly clear. Winds west to southwesterly 20 to 30 km/h becoming light in the late evening.",
        "icon_code": 3,
        "precipitation_prob": "5%",
        "precis": "Mostly clear.",
        "temp_max": null,
        "temp_min": null
      }
    },
    "2025-12-23": {
      "1": {
        "forecast": "Cloudy. Medium chance of showers, most likely in the morning. Winds west to southwesterly 20 to 30 km/h becoming light in the late evening.",
        "icon_code": 11,
        "precipitation_prob": "60%",
        "precis": "Shower or two.",
        "temp_max": 19,
        "temp_min": 10
      }
    },
    "2025-12-24": {
      "2": {
        "forecast": "Cloudy. Medium chance of showers, most likely in the morning and afternoon. Winds northwest to southwesterly 25 to 40 km/h becoming southwesterly 25 to 35 km/h in the evening then tending westerly 15 to 25 km/h in the late evening.",
        "icon_code": 17,
        "precipitation_prob": "40%",
        "precis": "Possible shower.",
        "temp_max": 19,
        "temp_min": 10
      }
    },
    "2025-12-25": {
      "3": {
        "forecast": "Cloudy. Slight chance of a shower in the morning and afternoon. Winds west to southwesterly 20 to 30 km/h.",
        "icon_code": 4,
        "precipitation_prob": "30%",
        "precis": "Cloudy.",
        "temp_max": 17,
        "temp_min": 10
      }
    },
    "2025-12-26": {
      "4": {
        "forecast": "Cloudy. Light winds.",
        "icon_code": 4,
        "precipitation_prob": "10%",
        "precis": "Cloudy.",
        "temp_max": 21,
        "temp_min": 9
      }
    },
    "2025-12-27": {
      "5": {
        "forecast": "Sunny. Light winds becoming easterly 15 to 25 km/h during the morning.",
        "icon_code": 1,
        "precipitation_prob": "5%",
        "precis": "Sunny.",
        "temp_max": 25,
        "temp_min": 8
      }
    },
    "2025-12-28": {
      "6": {
        "forecast": "Sunny. Winds easterly 15 to 20 km/h.",
        "icon_code": 1,
        "precipitation_prob": "0%",
        "precis": "Sunny.",
        "temp_max": 31,
        "temp_min": 11
      }
    },
    "2025-12-29": {
      "7": {
        "forecast": "Partly cloudy. Light winds.",
        "icon_code": 3,
        "precipitation_prob": "10%",
        "precis": "Partly cloudy.",
        "temp_max": 34,
        "temp_min": 14
      }
    }
  },
  "product_id": "IDV10712",
  "state": "VIC",
  "timezone": "EDT"
}